{
  "meta": {
    "version": 2,
    "updatedAt": "2026-03-04T16:12:44.192Z"
  },
  "documents": [
    {
      "id": "35eaf133-23a2-4daf-abee-027a2aba621d",
      "sourcePath": "2026.1.19-29平顶山、太原茗视光、麦迪格、/结账单20260127.pdf",
      "originalName": "结账单20260127.pdf",
      "storedFilePath": "/uploads/1772612969698-29901731-结账单20260127.pdf",
      "ext": ".pdf",
      "mimeType": "application/pdf",
      "fileSize": 35649,
      "docCategory": "INVOICE",
      "docSubType": "TAXI_TICKET",
      "processingStatus": "SUCCESS",
      "title": "结账单20260127.pdf",
      "tags": [
        "其他",
        "TAXI_TICKET",
        "INVOICE"
      ],
      "commonFields": {
        "invoiceType": "未识别类型",
        "invoiceDate": "2026-01-22",
        "amount": 0,
        "amountExcludingTax": null,
        "taxAmount": null,
        "currency": "CNY",
        "invoiceCode": "",
        "invoiceNumber": "",
        "checkCode": "",
        "machineCode": "",
        "sellerName": "",
        "sellerTaxNumber": "",
        "purchaserName": "",
        "purchaserTaxNumber": "",
        "routeFrom": "",
        "routeTo": "",
        "travelerName": "",
        "seatClass": "",
        "expenseCategory": "其他",
        "occurredRegion": ""
      },
      "extraFields": {
        "plainText": "",
        "candidates": [
          {
            "sourceIndex": 0,
            "sourceType": "网约车行程单",
            "root": {
              "serviceProvider": "",
              "applicationDate": "2026-01-22",
              "startTime": "",
              "endTime": "",
              "phoneNumber": "",
              "totalAmount": "",
              "rideDetails": [
                {
                  "Number": "",
                  "carType": "",
                  "pickUpTime": "",
                  "city": "",
                  "startPlace": "",
                  "endPlace": "",
                  "mileage": "",
                  "amount": "",
                  "remarks": ""
                },
                {
                  "Number": "",
                  "carType": "",
                  "pickUpTime": "",
                  "city": "",
                  "startPlace": "",
                  "endPlace": "",
                  "mileage": "",
                  "amount": "",
                  "remarks": ""
                }
              ]
            }
          }
        ],
        "rawPayload": {
          "algo_version": "",
          "count": 1,
          "height": 4092,
          "orgHeight": 4092,
          "orgWidth": 2893,
          "subMsgs": [
            {
              "index": 1,
              "op": "online_taxi_itinerary",
              "result": {
                "algo_version": "",
                "angle": 0,
                "data": {
                  "serviceProvider": "",
                  "applicationDate": "2026-01-22",
                  "startTime": "",
                  "endTime": "",
                  "phoneNumber": "",
                  "totalAmount": "",
                  "rideDetails": [
                    {
                      "Number": "",
                      "carType": "",
                      "pickUpTime": "",
                      "city": "",
                      "startPlace": "",
                      "endPlace": "",
                      "mileage": "",
                      "amount": "",
                      "remarks": ""
                    },
                    {
                      "Number": "",
                      "carType": "",
                      "pickUpTime": "",
                      "city": "",
                      "startPlace": "",
                      "endPlace": "",
                      "mileage": "",
                      "amount": "",
                      "remarks": ""
                    }
                  ]
                },
                "ftype": 1,
                "height": 1620,
                "orgHeight": 1620,
                "orgWidth": 2714,
                "prism_keyValueInfo": [
                  {
                    "key": "serviceProvider",
                    "keyProb": 100,
                    "value": "",
                    "valueProb": 100
                  },
                  {
                    "key": "applicationDate",
                    "keyProb": 100,
                    "value": "2026-01-22",
                    "valuePos": [
                      {
                        "x": 1849,
                        "y": 694
                      },
                      {
                        "x": 2154,
                        "y": 694
                      },
                      {
                        "x": 2154,
                        "y": 750
                      },
                      {
                        "x": 1849,
                        "y": 750
                      }
                    ],
                    "valueProb": 100
                  },
                  {
                    "key": "startTime",
                    "keyProb": 100,
                    "value": "",
                    "valueProb": 100
                  },
                  {
                    "key": "endTime",
                    "keyProb": 100,
                    "value": "",
                    "valuePos": [
                      {
                        "x": 916,
                        "y": 127
                      },
                      {
                        "x": 1846,
                        "y": 125
                      },
                      {
                        "x": 1847,
                        "y": 217
                      },
                      {
                        "x": 916,
                        "y": 219
                      }
                    ],
                    "valueProb": 100
                  },
                  {
                    "key": "phoneNumber",
                    "keyProb": 100,
                    "value": "",
                    "valuePos": [
                      {
                        "x": 111,
                        "y": 546
                      },
                      {
                        "x": 1472,
                        "y": 172
                      },
                      {
                        "x": 1505,
                        "y": 291
                      },
                      {
                        "x": 144,
                        "y": 666
                      }
                    ],
                    "valueProb": 100
                  },
                  {
                    "key": "totalAmount",
                    "keyProb": 100,
                    "value": "",
                    "valueProb": 100
                  },
                  {
                    "key": "rideDetails",
                    "keyProb": 100,
                    "value": "[{\"Number\":\"\",\"carType\":\"\",\"pickUpTime\":\"\",\"city\":\"\",\"startPlace\":\"\",\"endPlace\":\"\",\"mileage\":\"\",\"amount\":\"\",\"remarks\":\"\"},{\"Number\":\"\",\"carType\":\"\",\"pickUpTime\":\"\",\"city\":\"\",\"startPlace\":\"\",\"endPlace\":\"\",\"mileage\":\"\",\"amount\":\"\",\"remarks\":\"\"}]",
                    "valueProb": 100
                  }
                ],
                "sliceRect": {
                  "x0": 57,
                  "y0": 80,
                  "x1": 2764,
                  "y1": 76,
                  "x2": 2770,
                  "y2": 1686,
                  "x3": 74,
                  "y3": 1695
                },
                "width": 2714
              },
              "sliceRect": {
                "x0": 57,
                "y0": 80,
                "x1": 2764,
                "y1": 76,
                "x2": 2770,
                "y2": 1686,
                "x3": 74,
                "y3": 1695
              },
              "type": "网约车行程单"
            }
          ],
          "width": 2893
        },
        "usedAction": "RecognizeMixedInvoices",
        "providerRequestId": "D478646D-E30A-5B9C-B7A5-687AF222367B",
        "providerCode": "",
        "providerMessage": ""
      },
      "createdAt": "2026-03-04T08:29:29.705Z",
      "importedAt": "2026-03-04T08:29:29.705Z"
    },
    {
      "id": "4cb4fa93-6566-433f-9be2-2ff964f36d52",
      "sourcePath": "2026.1.19-29平顶山、太原茗视光、麦迪格、/平顶山郑州，太原.docx",
      "originalName": "平顶山郑州，太原.docx",
      "storedFilePath": "/uploads/1772612971133-614451409-平顶山郑州，太原.docx",
      "ext": ".docx",
      "mimeType": "application/vnd.openxmlformats-officedocument.wordprocessingml.document",
      "fileSize": 770748,
      "docCategory": "SUMMARY",
      "docSubType": "UNKNOWN",
      "processingStatus": "SUCCESS",
      "title": "平顶山郑州，太原.docx",
      "tags": [
        "SUMMARY",
        "其他",
        "UNKNOWN"
      ],
      "commonFields": {
        "invoiceType": "汇总文档",
        "invoiceDate": "",
        "amount": null,
        "amountExcludingTax": null,
        "taxAmount": null,
        "currency": "CNY",
        "invoiceCode": "",
        "invoiceNumber": "",
        "checkCode": "",
        "machineCode": "",
        "sellerName": "",
        "sellerTaxNumber": "",
        "purchaserName": "",
        "purchaserTaxNumber": "",
        "routeFrom": "",
        "routeTo": "",
        "travelerName": "",
        "seatClass": "",
        "expenseCategory": "其他",
        "occurredRegion": ""
      },
      "extraFields": {
        "plainText": "",
        "rawPayload": {}
      },
      "createdAt": "2026-03-04T08:29:31.147Z",
      "importedAt": "2026-03-04T08:29:31.147Z"
    },
    {
      "id": "29385e1d-6d9f-4ef9-b82e-761ec7a992da",
      "sourcePath": "2026.1.30-1渭南、禹州、郑州/渭南、禹州、郑州高铁.docx",
      "originalName": "渭南、禹州、郑州高铁.docx",
      "storedFilePath": "/uploads/1772613003844-746755917-渭南、禹州、郑州高铁.docx",
      "ext": ".docx",
      "mimeType": "application/vnd.openxmlformats-officedocument.wordprocessingml.document",
      "fileSize": 425169,
      "docCategory": "SUMMARY",
      "docSubType": "TRAIN_TICKET",
      "processingStatus": "SUCCESS",
      "title": "渭南、禹州、郑州高铁.docx",
      "tags": [
        "SUMMARY",
        "交通-火车",
        "TRAIN_TICKET"
      ],
      "commonFields": {
        "invoiceType": "汇总文档",
        "invoiceDate": "",
        "amount": null,
        "amountExcludingTax": null,
        "taxAmount": null,
        "currency": "CNY",
        "invoiceCode": "",
        "invoiceNumber": "",
        "checkCode": "",
        "machineCode": "",
        "sellerName": "",
        "sellerTaxNumber": "",
        "purchaserName": "",
        "purchaserTaxNumber": "",
        "routeFrom": "",
        "routeTo": "",
        "travelerName": "",
        "seatClass": "",
        "expenseCategory": "交通-火车",
        "occurredRegion": ""
      },
      "extraFields": {
        "plainText": "",
        "rawPayload": {}
      },
      "createdAt": "2026-03-04T08:30:03.856Z",
      "importedAt": "2026-03-04T08:30:03.856Z"
    },
    {
      "id": "75c740f6-ef65-462b-ad07-2568c318c9c5",
      "sourcePath": "2026.2.2-5北京、青岛培训/2026.1.8-16青岛、漯河、禹州、麦迪格/青岛、漯河、许昌高铁.docx",
      "originalName": "青岛、漯河、许昌高铁.docx",
      "storedFilePath": "/uploads/1772613020830-749082207-青岛、漯河、许昌高铁.docx",
      "ext": ".docx",
      "mimeType": "application/vnd.openxmlformats-officedocument.wordprocessingml.document",
      "fileSize": 1099259,
      "docCategory": "SUMMARY",
      "docSubType": "TRAIN_TICKET",
      "processingStatus": "SUCCESS",
      "title": "青岛、漯河、许昌高铁.docx",
      "tags": [
        "SUMMARY",
        "交通-火车",
        "TRAIN_TICKET"
      ],
      "commonFields": {
        "invoiceType": "汇总文档",
        "invoiceDate": "",
        "amount": null,
        "amountExcludingTax": null,
        "taxAmount": null,
        "currency": "CNY",
        "invoiceCode": "",
        "invoiceNumber": "",
        "checkCode": "",
        "machineCode": "",
        "sellerName": "",
        "sellerTaxNumber": "",
        "purchaserName": "",
        "purchaserTaxNumber": "",
        "routeFrom": "",
        "routeTo": "",
        "travelerName": "",
        "seatClass": "",
        "expenseCategory": "交通-火车",
        "occurredRegion": ""
      },
      "extraFields": {
        "plainText": "",
        "rawPayload": {}
      },
      "createdAt": "2026-03-04T08:30:20.852Z",
      "importedAt": "2026-03-04T08:30:20.852Z"
    },
    {
      "id": "7dcf59ec-cdff-46c9-9f62-1525e3d6280c",
      "sourcePath": "2026.2.2-5北京、青岛培训/青岛高铁.docx",
      "originalName": "青岛高铁.docx",
      "storedFilePath": "/uploads/1772613057387-200109932-青岛高铁.docx",
      "ext": ".docx",
      "mimeType": "application/vnd.openxmlformats-officedocument.wordprocessingml.document",
      "fileSize": 190208,
      "docCategory": "SUMMARY",
      "docSubType": "TRAIN_TICKET",
      "processingStatus": "SUCCESS",
      "title": "青岛高铁.docx",
      "tags": [
        "SUMMARY",
        "交通-火车",
        "TRAIN_TICKET"
      ],
      "commonFields": {
        "invoiceType": "汇总文档",
        "invoiceDate": "",
        "amount": null,
        "amountExcludingTax": null,
        "taxAmount": null,
        "currency": "CNY",
        "invoiceCode": "",
        "invoiceNumber": "",
        "checkCode": "",
        "machineCode": "",
        "sellerName": "",
        "sellerTaxNumber": "",
        "purchaserName": "",
        "purchaserTaxNumber": "",
        "routeFrom": "",
        "routeTo": "",
        "travelerName": "",
        "seatClass": "",
        "expenseCategory": "交通-火车",
        "occurredRegion": ""
      },
      "extraFields": {
        "plainText": "",
        "rawPayload": {}
      },
      "createdAt": "2026-03-04T08:30:57.395Z",
      "importedAt": "2026-03-04T08:30:57.395Z"
    },
    {
      "id": "1364ec64-b1c3-4994-8bdf-4f37d1cdd6da",
      "sourcePath": "2026.2.8-14河南地区/河南出差.docx",
      "originalName": "河南出差.docx",
      "storedFilePath": "/uploads/1772613067122-688939864-河南出差.docx",
      "ext": ".docx",
      "mimeType": "application/vnd.openxmlformats-officedocument.wordprocessingml.document",
      "fileSize": 762773,
      "docCategory": "SUMMARY",
      "docSubType": "TRAVEL_SUMMARY",
      "processingStatus": "SUCCESS",
      "title": "河南出差.docx",
      "tags": [
        "SUMMARY",
        "其他",
        "TRAVEL_SUMMARY"
      ],
      "commonFields": {
        "invoiceType": "汇总文档",
        "invoiceDate": "",
        "amount": null,
        "amountExcludingTax": null,
        "taxAmount": null,
        "currency": "CNY",
        "invoiceCode": "",
        "invoiceNumber": "",
        "checkCode": "",
        "machineCode": "",
        "sellerName": "",
        "sellerTaxNumber": "",
        "purchaserName": "",
        "purchaserTaxNumber": "",
        "routeFrom": "",
        "routeTo": "",
        "travelerName": "",
        "seatClass": "",
        "expenseCategory": "其他",
        "occurredRegion": ""
      },
      "extraFields": {
        "plainText": "",
        "rawPayload": {}
      },
      "createdAt": "2026-03-04T08:31:07.137Z",
      "importedAt": "2026-03-04T08:31:07.137Z"
    },
    {
      "id": "9207975c-8ad0-436e-911e-b0f3edbd9f56",
      "sourcePath": "upload/764_26112000000068159896_科宏昌（北京）医疗仪器有限公司.pdf",
      "originalName": "764_26112000000068159896_科宏昌（北京）医疗仪器有限公司.pdf",
      "storedFilePath": "/uploads/1772632295013-846132318.pdf",
      "ext": ".pdf",
      "mimeType": "application/pdf",
      "fileSize": 145243,
      "docCategory": "INVOICE",
      "docSubType": "VAT_INVOICE",
      "processingStatus": "SUCCESS",
      "title": "电子发票(普通发票)",
      "tags": [
        "餐饮",
        "VAT_INVOICE",
        "INVOICE"
      ],
      "commonFields": {
        "invoiceType": "数电普通发票",
        "invoiceDate": "2026-01-06",
        "amount": 764,
        "amountExcludingTax": 756.44,
        "taxAmount": 7.56,
        "currency": "CNY",
        "invoiceCode": "",
        "invoiceNumber": "26112000000068159896",
        "checkCode": "",
        "machineCode": "",
        "sellerName": "北京浩扬餐饮管理有限公司",
        "sellerTaxNumber": "91110105MA009X0B64",
        "purchaserName": "科宏昌(北京)医疗仪器有限公司",
        "purchaserTaxNumber": "91110105675701542D",
        "routeFrom": "",
        "routeTo": "",
        "travelerName": "",
        "seatClass": "",
        "expenseCategory": "餐饮",
        "occurredRegion": ""
      },
      "extraFields": {
        "plainText": "",
        "candidates": [
          {
            "sourceIndex": 0,
            "sourceType": "增值税发票",
            "root": {
              "invoiceCode": "",
              "invoiceNumber": "26112000000068159896",
              "printedInvoiceCode": "",
              "printedInvoiceNumber": "",
              "invoiceDate": "2026年01月06日",
              "machineCode": "",
              "checkCode": "",
              "purchaserName": "科宏昌(北京)医疗仪器有限公司",
              "purchaserTaxNumber": "91110105675701542D",
              "purchaserContactInfo": "",
              "purchaserBankAccountInfo": "",
              "passwordArea": "",
              "invoiceAmountPreTax": "756.44",
              "invoiceTax": "7.56",
              "totalAmountInWords": "柒佰陆拾肆圆整",
              "totalAmount": "764.00",
              "sellerName": "北京浩扬餐饮管理有限公司",
              "sellerTaxNumber": "91110105MA009X0B64",
              "sellerContactInfo": "",
              "sellerBankAccountInfo": "",
              "recipient": "",
              "reviewer": "",
              "drawer": "刘国辉",
              "remarks": "",
              "title": "电子发票(普通发票)",
              "formType": "",
              "invoiceType": "数电普通发票",
              "specialTag": "",
              "invoiceDetails": [
                {
                  "itemName": "*餐饮服务*餐饮服务",
                  "specification": "",
                  "unit": "",
                  "quantity": "",
                  "unitPrice": "",
                  "amount": "756.44",
                  "taxRate": "1%",
                  "tax": "7.56"
                }
              ]
            }
          }
        ],
        "rawPayload": {
          "algo_version": "",
          "count": 1,
          "height": 2728,
          "orgHeight": 2728,
          "orgWidth": 4092,
          "subMsgs": [
            {
              "index": 1,
              "op": "invoice",
              "result": {
                "algo_version": "",
                "angle": 0,
                "codes": [
                  {
                    "data": "01,32,,26112000000068159896,764.00,20260106,,9EED",
                    "points": [
                      {
                        "x": 124,
                        "y": 117
                      },
                      {
                        "x": 511,
                        "y": 117
                      },
                      {
                        "x": 511,
                        "y": 507
                      },
                      {
                        "x": 124,
                        "y": 507
                      }
                    ],
                    "type": "QRcode"
                  }
                ],
                "data": {
                  "invoiceCode": "",
                  "invoiceNumber": "26112000000068159896",
                  "printedInvoiceCode": "",
                  "printedInvoiceNumber": "",
                  "invoiceDate": "2026年01月06日",
                  "machineCode": "",
                  "checkCode": "",
                  "purchaserName": "科宏昌(北京)医疗仪器有限公司",
                  "purchaserTaxNumber": "91110105675701542D",
                  "purchaserContactInfo": "",
                  "purchaserBankAccountInfo": "",
                  "passwordArea": "",
                  "invoiceAmountPreTax": "756.44",
                  "invoiceTax": "7.56",
                  "totalAmountInWords": "柒佰陆拾肆圆整",
                  "totalAmount": "764.00",
                  "sellerName": "北京浩扬餐饮管理有限公司",
                  "sellerTaxNumber": "91110105MA009X0B64",
                  "sellerContactInfo": "",
                  "sellerBankAccountInfo": "",
                  "recipient": "",
                  "reviewer": "",
                  "drawer": "刘国辉",
                  "remarks": "",
                  "title": "电子发票(普通发票)",
                  "formType": "",
                  "invoiceType": "数电普通发票",
                  "specialTag": "",
                  "invoiceDetails": [
                    {
                      "itemName": "*餐饮服务*餐饮服务",
                      "specification": "",
                      "unit": "",
                      "quantity": "",
                      "unitPrice": "",
                      "amount": "756.44",
                      "taxRate": "1%",
                      "tax": "7.56"
                    }
                  ]
                },
                "ftype": 0,
                "height": 2529,
                "orgHeight": 2529,
                "orgWidth": 3955,
                "prism_keyValueInfo": [
                  {
                    "key": "invoiceCode",
                    "keyProb": 100,
                    "value": "",
                    "valueProb": 100
                  },
                  {
                    "key": "invoiceNumber",
                    "keyProb": 100,
                    "value": "26112000000068159896",
                    "valuePos": [
                      {
                        "x": 3235,
                        "y": 120
                      },
                      {
                        "x": 3870,
                        "y": 121
                      },
                      {
                        "x": 3870,
                        "y": 190
                      },
                      {
                        "x": 3235,
                        "y": 189
                      }
                    ],
                    "valueProb": 100
                  },
                  {
                    "key": "printedInvoiceCode",
                    "keyProb": 100,
                    "value": "",
                    "valueProb": 100
                  },
                  {
                    "key": "printedInvoiceNumber",
                    "keyProb": 100,
                    "value": "",
                    "valueProb": 100
                  },
                  {
                    "key": "invoiceDate",
                    "keyProb": 98,
                    "value": "2026年01月06日",
                    "valuePos": [
                      {
                        "x": 3237,
                        "y": 237
                      },
                      {
                        "x": 3680,
                        "y": 238
                      },
                      {
                        "x": 3680,
                        "y": 310
                      },
                      {
                        "x": 3237,
                        "y": 310
                      }
                    ],
                    "valueProb": 98
                  },
                  {
                    "key": "machineCode",
                    "keyProb": 100,
                    "value": "",
                    "valueProb": 100
                  },
                  {
                    "key": "checkCode",
                    "keyProb": 100,
                    "value": "",
                    "valueProb": 100
                  },
                  {
                    "key": "purchaserName",
                    "keyProb": 100,
                    "value": "科宏昌(北京)医疗仪器有限公司",
                    "valuePos": [
                      {
                        "x": 309,
                        "y": 558
                      },
                      {
                        "x": 1252,
                        "y": 556
                      },
                      {
                        "x": 1252,
                        "y": 633
                      },
                      {
                        "x": 310,
                        "y": 635
                      }
                    ],
                    "valueProb": 100
                  },
                  {
                    "key": "purchaserTaxNumber",
                    "keyProb": 100,
                    "value": "91110105675701542D",
                    "valuePos": [
                      {
                        "x": 983,
                        "y": 752
                      },
                      {
                        "x": 1886,
                        "y": 752
                      },
                      {
                        "x": 1886,
                        "y": 846
                      },
                      {
                        "x": 983,
                        "y": 846
                      }
                    ],
                    "valueProb": 100
                  },
                  {
                    "key": "purchaserContactInfo",
                    "keyProb": 100,
                    "value": "",
                    "valueProb": 100
                  },
                  {
                    "key": "purchaserBankAccountInfo",
                    "keyProb": 100,
                    "value": "",
                    "valueProb": 100
                  },
                  {
                    "key": "passwordArea",
                    "keyProb": 100,
                    "value": "",
                    "valueProb": 100
                  },
                  {
                    "key": "invoiceAmountPreTax",
                    "keyProb": 100,
                    "value": "756.44",
                    "valuePos": [
                      {
                        "x": 2686,
                        "y": 1695
                      },
                      {
                        "x": 2930,
                        "y": 1695
                      },
                      {
                        "x": 2930,
                        "y": 1761
                      },
                      {
                        "x": 2686,
                        "y": 1761
                      }
                    ],
                    "valueProb": 100
                  },
                  {
                    "key": "invoiceTax",
                    "keyProb": 100,
                    "value": "7.56",
                    "valuePos": [
                      {
                        "x": 3760,
                        "y": 1697
                      },
                      {
                        "x": 3940,
                        "y": 1695
                      },
                      {
                        "x": 3940,
                        "y": 1760
                      },
                      {
                        "x": 3761,
                        "y": 1761
                      }
                    ],
                    "valueProb": 100
                  },
                  {
                    "key": "totalAmountInWords",
                    "keyProb": 100,
                    "value": "柒佰陆拾肆圆整",
                    "valuePos": [
                      {
                        "x": 1151,
                        "y": 1811
                      },
                      {
                        "x": 1603,
                        "y": 1809
                      },
                      {
                        "x": 1603,
                        "y": 1886
                      },
                      {
                        "x": 1152,
                        "y": 1889
                      }
                    ],
                    "valueProb": 100
                  },
                  {
                    "key": "totalAmount",
                    "keyProb": 100,
                    "value": "764.00",
                    "valuePos": [
                      {
                        "x": 2957,
                        "y": 1810
                      },
                      {
                        "x": 3246,
                        "y": 1808
                      },
                      {
                        "x": 3247,
                        "y": 1884
                      },
                      {
                        "x": 2957,
                        "y": 1887
                      }
                    ],
                    "valueProb": 100
                  },
                  {
                    "key": "sellerName",
                    "keyProb": 100,
                    "value": "北京浩扬餐饮管理有限公司",
                    "valuePos": [
                      {
                        "x": 2264,
                        "y": 557
                      },
                      {
                        "x": 3019,
                        "y": 557
                      },
                      {
                        "x": 3019,
                        "y": 635
                      },
                      {
                        "x": 2264,
                        "y": 635
                      }
                    ],
                    "valueProb": 100
                  },
                  {
                    "key": "sellerTaxNumber",
                    "keyProb": 100,
                    "value": "91110105MA009X0B64",
                    "valuePos": [
                      {
                        "x": 2945,
                        "y": 753
                      },
                      {
                        "x": 3839,
                        "y": 753
                      },
                      {
                        "x": 3839,
                        "y": 845
                      },
                      {
                        "x": 2945,
                        "y": 845
                      }
                    ],
                    "valueProb": 100
                  },
                  {
                    "key": "sellerContactInfo",
                    "keyProb": 100,
                    "value": "",
                    "valueProb": 100
                  },
                  {
                    "key": "sellerBankAccountInfo",
                    "keyProb": 100,
                    "value": "",
                    "valueProb": 100
                  },
                  {
                    "key": "recipient",
                    "keyProb": 100,
                    "value": "",
                    "valueProb": 100
                  },
                  {
                    "key": "reviewer",
                    "keyProb": 100,
                    "value": "",
                    "valueProb": 100
                  },
                  {
                    "key": "drawer",
                    "keyProb": 100,
                    "value": "刘国辉",
                    "valuePos": [
                      {
                        "x": 549,
                        "y": 2429
                      },
                      {
                        "x": 751,
                        "y": 2426
                      },
                      {
                        "x": 752,
                        "y": 2503
                      },
                      {
                        "x": 549,
                        "y": 2505
                      }
                    ],
                    "valueProb": 100
                  },
                  {
                    "key": "remarks",
                    "keyProb": 100,
                    "value": "",
                    "valueProb": 100
                  },
                  {
                    "key": "title",
                    "keyProb": 100,
                    "value": "电子发票(普通发票)",
                    "valuePos": [
                      {
                        "x": 1260,
                        "y": 59
                      },
                      {
                        "x": 2562,
                        "y": 60
                      },
                      {
                        "x": 2562,
                        "y": 208
                      },
                      {
                        "x": 1260,
                        "y": 207
                      }
                    ],
                    "valueProb": 100
                  },
                  {
                    "key": "formType",
                    "keyProb": 100,
                    "value": "",
                    "valueProb": 100
                  },
                  {
                    "key": "invoiceType",
                    "keyProb": 100,
                    "value": "数电普通发票",
                    "valuePos": [
                      {
                        "x": 1260,
                        "y": 59
                      },
                      {
                        "x": 2562,
                        "y": 60
                      },
                      {
                        "x": 2562,
                        "y": 208
                      },
                      {
                        "x": 1260,
                        "y": 207
                      }
                    ],
                    "valueProb": 100
                  },
                  {
                    "key": "specialTag",
                    "keyProb": 100,
                    "value": "",
                    "valueProb": 100
                  },
                  {
                    "key": "invoiceDetails",
                    "keyProb": 100,
                    "value": "[{\"itemName\":\"*餐饮服务*餐饮服务\",\"specification\":\"\",\"unit\":\"\",\"quantity\":\"\",\"unitPrice\":\"\",\"amount\":\"756.44\",\"taxRate\":\"1%\",\"tax\":\"7.56\"}]",
                    "valueProb": 100
                  }
                ],
                "sliceRect": {
                  "x0": 68,
                  "y0": 92,
                  "x1": 4014,
                  "y1": 92,
                  "x2": 4019,
                  "y2": 2620,
                  "x3": 65,
                  "y3": 2619
                },
                "width": 3955
              },
              "sliceRect": {
                "x0": 68,
                "y0": 92,
                "x1": 4014,
                "y1": 92,
                "x2": 4019,
                "y2": 2620,
                "x3": 65,
                "y3": 2619
              },
              "type": "增值税发票"
            }
          ],
          "width": 4092
        },
        "usedAction": "RecognizeMixedInvoices",
        "providerRequestId": "1F7FD861-73CD-52F8-B3CF-8B3A74E10FE7",
        "providerCode": "",
        "providerMessage": ""
      },
      "createdAt": "2026-03-04T13:51:35.019Z",
      "importedAt": "2026-03-04T13:51:35.019Z"
    },
    {
      "id": "716f5ed1-e8ba-4b0b-922e-e0ef1806a57a",
      "sourcePath": "upload/255.00元_2026.01.03_北京小大董三里屯餐饮有限公司_26112000000016867066_.pdf",
      "originalName": "255.00元_2026.01.03_北京小大董三里屯餐饮有限公司_26112000000016867066_.pdf",
      "storedFilePath": "/uploads/1772632311953-529723846.pdf",
      "ext": ".pdf",
      "mimeType": "application/pdf",
      "fileSize": 144931,
      "docCategory": "INVOICE",
      "docSubType": "VAT_INVOICE",
      "processingStatus": "SUCCESS",
      "title": "电子发票(普通发票)",
      "tags": [
        "餐饮",
        "VAT_INVOICE",
        "INVOICE"
      ],
      "commonFields": {
        "invoiceType": "数电普通发票",
        "invoiceDate": "2026-01-03",
        "amount": 255,
        "amountExcludingTax": 240.57,
        "taxAmount": 14.43,
        "currency": "CNY",
        "invoiceCode": "",
        "invoiceNumber": "26112000000016867066",
        "checkCode": "",
        "machineCode": "",
        "sellerName": "北京小大董三里屯餐饮有限公司",
        "sellerTaxNumber": "91110105MA01UHAT9W",
        "purchaserName": "科宏昌(北京)医疗仪器有限公司",
        "purchaserTaxNumber": "91110105675701542D",
        "routeFrom": "",
        "routeTo": "",
        "travelerName": "",
        "seatClass": "",
        "expenseCategory": "餐饮",
        "occurredRegion": ""
      },
      "extraFields": {
        "plainText": "",
        "candidates": [
          {
            "sourceIndex": 0,
            "sourceType": "增值税发票",
            "root": {
              "invoiceCode": "",
              "invoiceNumber": "26112000000016867066",
              "printedInvoiceCode": "",
              "printedInvoiceNumber": "",
              "invoiceDate": "2026年01月03日",
              "machineCode": "",
              "checkCode": "",
              "purchaserName": "科宏昌(北京)医疗仪器有限公司",
              "purchaserTaxNumber": "91110105675701542D",
              "purchaserContactInfo": "",
              "purchaserBankAccountInfo": "",
              "passwordArea": "",
              "invoiceAmountPreTax": "240.57",
              "invoiceTax": "14.43",
              "totalAmountInWords": "贰佰伍拾伍圆整",
              "totalAmount": "255.00",
              "sellerName": "北京小大董三里屯餐饮有限公司",
              "sellerTaxNumber": "91110105MA01UHAT9W",
              "sellerContactInfo": "",
              "sellerBankAccountInfo": "",
              "recipient": "",
              "reviewer": "",
              "drawer": "赵磊",
              "remarks": "",
              "title": "电子发票(普通发票)",
              "formType": "",
              "invoiceType": "数电普通发票",
              "specialTag": "",
              "invoiceDetails": [
                {
                  "itemName": "*餐饮服务*餐饮服务",
                  "specification": "",
                  "unit": "",
                  "quantity": "1",
                  "unitPrice": "240.57",
                  "amount": "240.57",
                  "taxRate": "6%",
                  "tax": "14.43"
                }
              ]
            }
          }
        ],
        "rawPayload": {
          "algo_version": "",
          "count": 1,
          "height": 2728,
          "orgHeight": 2728,
          "orgWidth": 4092,
          "subMsgs": [
            {
              "index": 1,
              "op": "invoice",
              "result": {
                "algo_version": "",
                "angle": 0,
                "codes": [
                  {
                    "data": "01,32,,26112000000016867066,255.00,20260103,,D694",
                    "points": [
                      {
                        "x": 124,
                        "y": 119
                      },
                      {
                        "x": 513,
                        "y": 119
                      },
                      {
                        "x": 513,
                        "y": 503
                      },
                      {
                        "x": 124,
                        "y": 503
                      }
                    ],
                    "type": "QRcode"
                  }
                ],
                "data": {
                  "invoiceCode": "",
                  "invoiceNumber": "26112000000016867066",
                  "printedInvoiceCode": "",
                  "printedInvoiceNumber": "",
                  "invoiceDate": "2026年01月03日",
                  "machineCode": "",
                  "checkCode": "",
                  "purchaserName": "科宏昌(北京)医疗仪器有限公司",
                  "purchaserTaxNumber": "91110105675701542D",
                  "purchaserContactInfo": "",
                  "purchaserBankAccountInfo": "",
                  "passwordArea": "",
                  "invoiceAmountPreTax": "240.57",
                  "invoiceTax": "14.43",
                  "totalAmountInWords": "贰佰伍拾伍圆整",
                  "totalAmount": "255.00",
                  "sellerName": "北京小大董三里屯餐饮有限公司",
                  "sellerTaxNumber": "91110105MA01UHAT9W",
                  "sellerContactInfo": "",
                  "sellerBankAccountInfo": "",
                  "recipient": "",
                  "reviewer": "",
                  "drawer": "赵磊",
                  "remarks": "",
                  "title": "电子发票(普通发票)",
                  "formType": "",
                  "invoiceType": "数电普通发票",
                  "specialTag": "",
                  "invoiceDetails": [
                    {
                      "itemName": "*餐饮服务*餐饮服务",
                      "specification": "",
                      "unit": "",
                      "quantity": "1",
                      "unitPrice": "240.57",
                      "amount": "240.57",
                      "taxRate": "6%",
                      "tax": "14.43"
                    }
                  ]
                },
                "ftype": 0,
                "height": 2536,
                "orgHeight": 2536,
                "orgWidth": 3960,
                "prism_keyValueInfo": [
                  {
                    "key": "invoiceCode",
                    "keyProb": 100,
                    "value": "",
                    "valueProb": 100
                  },
                  {
                    "key": "invoiceNumber",
                    "keyProb": 100,
                    "value": "26112000000016867066",
                    "valuePos": [
                      {
                        "x": 3238,
                        "y": 124
                      },
                      {
                        "x": 3872,
                        "y": 125
                      },
                      {
                        "x": 3872,
                        "y": 194
                      },
                      {
                        "x": 3238,
                        "y": 193
                      }
                    ],
                    "valueProb": 100
                  },
                  {
                    "key": "printedInvoiceCode",
                    "keyProb": 100,
                    "value": "",
                    "valueProb": 100
                  },
                  {
                    "key": "printedInvoiceNumber",
                    "keyProb": 100,
                    "value": "",
                    "valueProb": 100
                  },
                  {
                    "key": "invoiceDate",
                    "keyProb": 100,
                    "value": "2026年01月03日",
                    "valuePos": [
                      {
                        "x": 3240,
                        "y": 241
                      },
                      {
                        "x": 3683,
                        "y": 242
                      },
                      {
                        "x": 3683,
                        "y": 315
                      },
                      {
                        "x": 3240,
                        "y": 315
                      }
                    ],
                    "valueProb": 100
                  },
                  {
                    "key": "machineCode",
                    "keyProb": 100,
                    "value": "",
                    "valueProb": 100
                  },
                  {
                    "key": "checkCode",
                    "keyProb": 100,
                    "value": "",
                    "valueProb": 100
                  },
                  {
                    "key": "purchaserName",
                    "keyProb": 100,
                    "value": "科宏昌(北京)医疗仪器有限公司",
                    "valuePos": [
                      {
                        "x": 314,
                        "y": 561
                      },
                      {
                        "x": 1254,
                        "y": 559
                      },
                      {
                        "x": 1254,
                        "y": 636
                      },
                      {
                        "x": 314,
                        "y": 637
                      }
                    ],
                    "valueProb": 100
                  },
                  {
                    "key": "purchaserTaxNumber",
                    "keyProb": 100,
                    "value": "91110105675701542D",
                    "valuePos": [
                      {
                        "x": 983,
                        "y": 755
                      },
                      {
                        "x": 1887,
                        "y": 754
                      },
                      {
                        "x": 1888,
                        "y": 850
                      },
                      {
                        "x": 984,
                        "y": 852
                      }
                    ],
                    "valueProb": 100
                  },
                  {
                    "key": "purchaserContactInfo",
                    "keyProb": 100,
                    "value": "",
                    "valueProb": 100
                  },
                  {
                    "key": "purchaserBankAccountInfo",
                    "keyProb": 100,
                    "value": "",
                    "valueProb": 100
                  },
                  {
                    "key": "passwordArea",
                    "keyProb": 100,
                    "value": "",
                    "valueProb": 100
                  },
                  {
                    "key": "invoiceAmountPreTax",
                    "keyProb": 99,
                    "value": "240.57",
                    "valuePos": [
                      {
                        "x": 2686,
                        "y": 1697
                      },
                      {
                        "x": 2932,
                        "y": 1696
                      },
                      {
                        "x": 2933,
                        "y": 1764
                      },
                      {
                        "x": 2687,
                        "y": 1765
                      }
                    ],
                    "valueProb": 99
                  },
                  {
                    "key": "invoiceTax",
                    "keyProb": 100,
                    "value": "14.43",
                    "valuePos": [
                      {
                        "x": 3733,
                        "y": 1700
                      },
                      {
                        "x": 3943,
                        "y": 1699
                      },
                      {
                        "x": 3944,
                        "y": 1764
                      },
                      {
                        "x": 3734,
                        "y": 1765
                      }
                    ],
                    "valueProb": 100
                  },
                  {
                    "key": "totalAmountInWords",
                    "keyProb": 100,
                    "value": "贰佰伍拾伍圆整",
                    "valuePos": [
                      {
                        "x": 1153,
                        "y": 1814
                      },
                      {
                        "x": 1603,
                        "y": 1812
                      },
                      {
                        "x": 1603,
                        "y": 1890
                      },
                      {
                        "x": 1154,
                        "y": 1893
                      }
                    ],
                    "valueProb": 100
                  },
                  {
                    "key": "totalAmount",
                    "keyProb": 100,
                    "value": "255.00",
                    "valuePos": [
                      {
                        "x": 2959,
                        "y": 1815
                      },
                      {
                        "x": 3247,
                        "y": 1812
                      },
                      {
                        "x": 3248,
                        "y": 1887
                      },
                      {
                        "x": 2959,
                        "y": 1889
                      }
                    ],
                    "valueProb": 100
                  },
                  {
                    "key": "sellerName",
                    "keyProb": 100,
                    "value": "北京小大董三里屯餐饮有限公司",
                    "valuePos": [
                      {
                        "x": 2264,
                        "y": 560
                      },
                      {
                        "x": 3143,
                        "y": 560
                      },
                      {
                        "x": 3143,
                        "y": 638
                      },
                      {
                        "x": 2264,
                        "y": 638
                      }
                    ],
                    "valueProb": 100
                  },
                  {
                    "key": "sellerTaxNumber",
                    "keyProb": 100,
                    "value": "91110105MA01UHAT9W",
                    "valuePos": [
                      {
                        "x": 2947,
                        "y": 757
                      },
                      {
                        "x": 3844,
                        "y": 757
                      },
                      {
                        "x": 3844,
                        "y": 849
                      },
                      {
                        "x": 2947,
                        "y": 849
                      }
                    ],
                    "valueProb": 100
                  },
                  {
                    "key": "sellerContactInfo",
                    "keyProb": 100,
                    "value": "",
                    "valueProb": 100
                  },
                  {
                    "key": "sellerBankAccountInfo",
                    "keyProb": 100,
                    "value": "",
                    "valueProb": 100
                  },
                  {
                    "key": "recipient",
                    "keyProb": 100,
                    "value": "",
                    "valueProb": 100
                  },
                  {
                    "key": "reviewer",
                    "keyProb": 100,
                    "value": "",
                    "valueProb": 100
                  },
                  {
                    "key": "drawer",
                    "keyProb": 100,
                    "value": "赵磊",
                    "valuePos": [
                      {
                        "x": 549,
                        "y": 2434
                      },
                      {
                        "x": 690,
                        "y": 2432
                      },
                      {
                        "x": 691,
                        "y": 2506
                      },
                      {
                        "x": 551,
                        "y": 2509
                      }
                    ],
                    "valueProb": 100
                  },
                  {
                    "key": "remarks",
                    "keyProb": 100,
                    "value": "",
                    "valueProb": 100
                  },
                  {
                    "key": "title",
                    "keyProb": 100,
                    "value": "电子发票(普通发票)",
                    "valuePos": [
                      {
                        "x": 1262,
                        "y": 64
                      },
                      {
                        "x": 2564,
                        "y": 65
                      },
                      {
                        "x": 2564,
                        "y": 212
                      },
                      {
                        "x": 1262,
                        "y": 211
                      }
                    ],
                    "valueProb": 100
                  },
                  {
                    "key": "formType",
                    "keyProb": 100,
                    "value": "",
                    "valueProb": 100
                  },
                  {
                    "key": "invoiceType",
                    "keyProb": 100,
                    "value": "数电普通发票",
                    "valuePos": [
                      {
                        "x": 1262,
                        "y": 64
                      },
                      {
                        "x": 2564,
                        "y": 65
                      },
                      {
                        "x": 2564,
                        "y": 212
                      },
                      {
                        "x": 1262,
                        "y": 211
                      }
                    ],
                    "valueProb": 100
                  },
                  {
                    "key": "specialTag",
                    "keyProb": 100,
                    "value": "",
                    "valueProb": 100
                  },
                  {
                    "key": "invoiceDetails",
                    "keyProb": 100,
                    "value": "[{\"itemName\":\"*餐饮服务*餐饮服务\",\"specification\":\"\",\"unit\":\"\",\"quantity\":\"1\",\"unitPrice\":\"240.57\",\"amount\":\"240.57\",\"taxRate\":\"6%\",\"tax\":\"14.43\"}]",
                    "valueProb": 100
                  }
                ],
                "sliceRect": {
                  "x0": 64,
                  "y0": 89,
                  "x1": 4017,
                  "y1": 88,
                  "x2": 4022,
                  "y2": 2622,
                  "x3": 63,
                  "y3": 2623
                },
                "width": 3960
              },
              "sliceRect": {
                "x0": 64,
                "y0": 89,
                "x1": 4017,
                "y1": 88,
                "x2": 4022,
                "y2": 2622,
                "x3": 63,
                "y3": 2623
              },
              "type": "增值税发票"
            }
          ],
          "width": 4092
        },
        "usedAction": "RecognizeMixedInvoices",
        "providerRequestId": "0B432DE8-FCB3-5970-93D3-06AF4B968577",
        "providerCode": "",
        "providerMessage": ""
      },
      "createdAt": "2026-03-04T13:51:51.956Z",
      "importedAt": "2026-03-04T13:51:51.956Z"
    },
    {
      "id": "70dcaf8e-bf99-4afb-a9a9-8c737fa64926",
      "sourcePath": "upload/dzfp_26412000000470619046_科宏昌（北京）医疗仪器有限公司_20260207182732.pdf",
      "originalName": "dzfp_26412000000470619046_科宏昌（北京）医疗仪器有限公司_20260207182732.pdf",
      "storedFilePath": "/uploads/1772639502134-244495579.pdf",
      "ext": ".pdf",
      "mimeType": "application/pdf",
      "fileSize": 70709,
      "docCategory": "INVOICE",
      "docSubType": "VAT_INVOICE",
      "processingStatus": "SUCCESS",
      "title": "电子发票(增值税专用发票)",
      "tags": [
        "住宿",
        "VAT_INVOICE",
        "INVOICE"
      ],
      "commonFields": {
        "invoiceType": "数电专用发票",
        "invoiceDate": "2026-02-07",
        "amount": 257.27,
        "amountExcludingTax": 254.72,
        "taxAmount": 2.55,
        "currency": "CNY",
        "invoiceCode": "",
        "invoiceNumber": "26412000000470619046",
        "checkCode": "",
        "machineCode": "",
        "sellerName": "许昌兴华酒店管理有限公司",
        "sellerTaxNumber": "91411002MA9MA11C53",
        "purchaserName": "科宏昌(北京)医疗仪器有限公司",
        "purchaserTaxNumber": "91110105675701542D",
        "routeFrom": "",
        "routeTo": "",
        "travelerName": "",
        "occurredRegion": "",
        "seatClass": "",
        "expenseCategory": "住宿"
      },
      "extraFields": {
        "plainText": "",
        "candidates": [
          {
            "sourceIndex": 0,
            "sourceType": "增值税发票",
            "root": {
              "invoiceCode": "",
              "invoiceNumber": "26412000000470619046",
              "printedInvoiceCode": "",
              "printedInvoiceNumber": "",
              "invoiceDate": "2026年02月07日",
              "machineCode": "",
              "checkCode": "",
              "purchaserName": "科宏昌(北京)医疗仪器有限公司",
              "purchaserTaxNumber": "91110105675701542D",
              "purchaserContactInfo": "",
              "purchaserBankAccountInfo": "",
              "passwordArea": "",
              "invoiceAmountPreTax": "254.72",
              "invoiceTax": "2.55",
              "totalAmountInWords": "贰佰伍拾柒圆贰角柒分",
              "totalAmount": "257.27",
              "sellerName": "许昌兴华酒店管理有限公司",
              "sellerTaxNumber": "91411002MA9MA11C53",
              "sellerContactInfo": "",
              "sellerBankAccountInfo": "",
              "recipient": "",
              "reviewer": "",
              "drawer": "王晋格",
              "remarks": "购买方地址:北京市朝阳区慈云寺北里118号楼8层801等[17]套内17层1701内03A、04、05室;电话:010-85752300;购方开户银行:招行北京东四环支行;银行账号:110906139710401;销售方地址:河南省许昌市魏都区颍昌大道绿洲梦想广场电话:0374-3137777;销方开户银行:中原银行股份有限公司许昌颖昌路支行;银行账号:411010010140035101;汉庭许昌胖东来生活广场酒店,入离日期:1-31至2-1,共1天,共1间",
              "title": "电子发票(增值税专用发票)",
              "formType": "",
              "invoiceType": "数电专用发票",
              "specialTag": "",
              "invoiceDetails": [
                {
                  "itemName": "*住宿服务*住宿费",
                  "specification": "高级双床房",
                  "unit": "天",
                  "quantity": "1",
                  "unitPrice": "254.7227722772277",
                  "amount": "254.72",
                  "taxRate": "1%",
                  "tax": "2.55"
                }
              ]
            }
          }
        ],
        "rawPayload": {
          "algo_version": "",
          "count": 1,
          "height": 2728,
          "orgHeight": 2728,
          "orgWidth": 4092,
          "subMsgs": [
            {
              "index": 1,
              "op": "invoice",
              "result": {
                "algo_version": "",
                "angle": 0,
                "codes": [
                  {
                    "data": "01,31,,26412000000470619046,257.27,20260207,,3871",
                    "points": [
                      {
                        "x": 120,
                        "y": 117
                      },
                      {
                        "x": 518,
                        "y": 117
                      },
                      {
                        "x": 518,
                        "y": 509
                      },
                      {
                        "x": 120,
                        "y": 509
                      }
                    ],
                    "type": "QRcode"
                  }
                ],
                "data": {
                  "invoiceCode": "",
                  "invoiceNumber": "26412000000470619046",
                  "printedInvoiceCode": "",
                  "printedInvoiceNumber": "",
                  "invoiceDate": "2026年02月07日",
                  "machineCode": "",
                  "checkCode": "",
                  "purchaserName": "科宏昌(北京)医疗仪器有限公司",
                  "purchaserTaxNumber": "91110105675701542D",
                  "purchaserContactInfo": "",
                  "purchaserBankAccountInfo": "",
                  "passwordArea": "",
                  "invoiceAmountPreTax": "254.72",
                  "invoiceTax": "2.55",
                  "totalAmountInWords": "贰佰伍拾柒圆贰角柒分",
                  "totalAmount": "257.27",
                  "sellerName": "许昌兴华酒店管理有限公司",
                  "sellerTaxNumber": "91411002MA9MA11C53",
                  "sellerContactInfo": "",
                  "sellerBankAccountInfo": "",
                  "recipient": "",
                  "reviewer": "",
                  "drawer": "王晋格",
                  "remarks": "购买方地址:北京市朝阳区慈云寺北里118号楼8层801等[17]套内17层1701内03A、04、05室;电话:010-85752300;购方开户银行:招行北京东四环支行;银行账号:110906139710401;销售方地址:河南省许昌市魏都区颍昌大道绿洲梦想广场电话:0374-3137777;销方开户银行:中原银行股份有限公司许昌颖昌路支行;银行账号:411010010140035101;汉庭许昌胖东来生活广场酒店,入离日期:1-31至2-1,共1天,共1间",
                  "title": "电子发票(增值税专用发票)",
                  "formType": "",
                  "invoiceType": "数电专用发票",
                  "specialTag": "",
                  "invoiceDetails": [
                    {
                      "itemName": "*住宿服务*住宿费",
                      "specification": "高级双床房",
                      "unit": "天",
                      "quantity": "1",
                      "unitPrice": "254.7227722772277",
                      "amount": "254.72",
                      "taxRate": "1%",
                      "tax": "2.55"
                    }
                  ]
                },
                "ftype": 0,
                "height": 2509,
                "orgHeight": 2509,
                "orgWidth": 3980,
                "prism_keyValueInfo": [
                  {
                    "key": "invoiceCode",
                    "keyProb": 100,
                    "value": "",
                    "valueProb": 100
                  },
                  {
                    "key": "invoiceNumber",
                    "keyProb": 100,
                    "value": "26412000000470619046",
                    "valuePos": [
                      {
                        "x": 3233,
                        "y": 112
                      },
                      {
                        "x": 3868,
                        "y": 113
                      },
                      {
                        "x": 3868,
                        "y": 183
                      },
                      {
                        "x": 3233,
                        "y": 182
                      }
                    ],
                    "valueProb": 100
                  },
                  {
                    "key": "printedInvoiceCode",
                    "keyProb": 100,
                    "value": "",
                    "valueProb": 100
                  },
                  {
                    "key": "printedInvoiceNumber",
                    "keyProb": 100,
                    "value": "",
                    "valueProb": 100
                  },
                  {
                    "key": "invoiceDate",
                    "keyProb": 100,
                    "value": "2026年02月07日",
                    "valuePos": [
                      {
                        "x": 3235,
                        "y": 228
                      },
                      {
                        "x": 3680,
                        "y": 229
                      },
                      {
                        "x": 3680,
                        "y": 301
                      },
                      {
                        "x": 3235,
                        "y": 301
                      }
                    ],
                    "valueProb": 100
                  },
                  {
                    "key": "machineCode",
                    "keyProb": 100,
                    "value": "",
                    "valueProb": 100
                  },
                  {
                    "key": "checkCode",
                    "keyProb": 100,
                    "value": "",
                    "valueProb": 100
                  },
                  {
                    "key": "purchaserName",
                    "keyProb": 100,
                    "value": "科宏昌(北京)医疗仪器有限公司",
                    "valuePos": [
                      {
                        "x": 307,
                        "y": 547
                      },
                      {
                        "x": 1254,
                        "y": 546
                      },
                      {
                        "x": 1254,
                        "y": 624
                      },
                      {
                        "x": 308,
                        "y": 625
                      }
                    ],
                    "valueProb": 100
                  },
                  {
                    "key": "purchaserTaxNumber",
                    "keyProb": 100,
                    "value": "91110105675701542D",
                    "valuePos": [
                      {
                        "x": 970,
                        "y": 745
                      },
                      {
                        "x": 1875,
                        "y": 745
                      },
                      {
                        "x": 1875,
                        "y": 842
                      },
                      {
                        "x": 970,
                        "y": 842
                      }
                    ],
                    "valueProb": 100
                  },
                  {
                    "key": "purchaserContactInfo",
                    "keyProb": 100,
                    "value": "",
                    "valueProb": 100
                  },
                  {
                    "key": "purchaserBankAccountInfo",
                    "keyProb": 100,
                    "value": "",
                    "valueProb": 100
                  },
                  {
                    "key": "passwordArea",
                    "keyProb": 100,
                    "value": "",
                    "valueProb": 100
                  },
                  {
                    "key": "invoiceAmountPreTax",
                    "keyProb": 99,
                    "value": "254.72",
                    "valuePos": [
                      {
                        "x": 2677,
                        "y": 1689
                      },
                      {
                        "x": 2919,
                        "y": 1689
                      },
                      {
                        "x": 2919,
                        "y": 1753
                      },
                      {
                        "x": 2677,
                        "y": 1753
                      }
                    ],
                    "valueProb": 99
                  },
                  {
                    "key": "invoiceTax",
                    "keyProb": 99,
                    "value": "2.55",
                    "valuePos": [
                      {
                        "x": 3761,
                        "y": 1691
                      },
                      {
                        "x": 3940,
                        "y": 1691
                      },
                      {
                        "x": 3940,
                        "y": 1753
                      },
                      {
                        "x": 3761,
                        "y": 1753
                      }
                    ],
                    "valueProb": 99
                  },
                  {
                    "key": "totalAmountInWords",
                    "keyProb": 97,
                    "value": "贰佰伍拾柒圆贰角柒分",
                    "valuePos": [
                      {
                        "x": 1152,
                        "y": 1804
                      },
                      {
                        "x": 1784,
                        "y": 1803
                      },
                      {
                        "x": 1784,
                        "y": 1881
                      },
                      {
                        "x": 1153,
                        "y": 1883
                      }
                    ],
                    "valueProb": 97
                  },
                  {
                    "key": "totalAmount",
                    "keyProb": 99,
                    "value": "257.27",
                    "valuePos": [
                      {
                        "x": 2946,
                        "y": 1806
                      },
                      {
                        "x": 3231,
                        "y": 1806
                      },
                      {
                        "x": 3231,
                        "y": 1881
                      },
                      {
                        "x": 2946,
                        "y": 1881
                      }
                    ],
                    "valueProb": 99
                  },
                  {
                    "key": "sellerName",
                    "keyProb": 98,
                    "value": "许昌兴华酒店管理有限公司",
                    "valuePos": [
                      {
                        "x": 2257,
                        "y": 546
                      },
                      {
                        "x": 3019,
                        "y": 546
                      },
                      {
                        "x": 3019,
                        "y": 625
                      },
                      {
                        "x": 2257,
                        "y": 625
                      }
                    ],
                    "valueProb": 98
                  },
                  {
                    "key": "sellerTaxNumber",
                    "keyProb": 100,
                    "value": "91411002MA9MA11C53",
                    "valuePos": [
                      {
                        "x": 2934,
                        "y": 746
                      },
                      {
                        "x": 3828,
                        "y": 746
                      },
                      {
                        "x": 3828,
                        "y": 839
                      },
                      {
                        "x": 2934,
                        "y": 839
                      }
                    ],
                    "valueProb": 100
                  },
                  {
                    "key": "sellerContactInfo",
                    "keyProb": 100,
                    "value": "",
                    "valueProb": 100
                  },
                  {
                    "key": "sellerBankAccountInfo",
                    "keyProb": 100,
                    "value": "",
                    "valueProb": 100
                  },
                  {
                    "key": "recipient",
                    "keyProb": 100,
                    "value": "",
                    "valueProb": 100
                  },
                  {
                    "key": "reviewer",
                    "keyProb": 100,
                    "value": "",
                    "valueProb": 100
                  },
                  {
                    "key": "drawer",
                    "keyProb": 100,
                    "value": "王晋格",
                    "valuePos": [
                      {
                        "x": 551,
                        "y": 2411
                      },
                      {
                        "x": 748,
                        "y": 2410
                      },
                      {
                        "x": 748,
                        "y": 2485
                      },
                      {
                        "x": 551,
                        "y": 2487
                      }
                    ],
                    "valueProb": 100
                  },
                  {
                    "key": "remarks",
                    "keyProb": 100,
                    "value": "购买方地址:北京市朝阳区慈云寺北里118号楼8层801等[17]套内17层1701内03A、04、05室;电话:010-85752300;购方开户银行:招行北京东四环支行;银行账号:110906139710401;销售方地址:河南省许昌市魏都区颍昌大道绿洲梦想广场电话:0374-3137777;销方开户银行:中原银行股份有限公司许昌颖昌路支行;银行账号:411010010140035101;汉庭许昌胖东来生活广场酒店,入离日期:1-31至2-1,共1天,共1间",
                    "valuePos": [
                      {
                        "x": 146,
                        "y": 1925
                      },
                      {
                        "x": 3308,
                        "y": 1926
                      },
                      {
                        "x": 3308,
                        "y": 2249
                      },
                      {
                        "x": 146,
                        "y": 2249
                      }
                    ],
                    "valueProb": 100
                  },
                  {
                    "key": "title",
                    "keyProb": 100,
                    "value": "电子发票(增值税专用发票)",
                    "valuePos": [
                      {
                        "x": 1047,
                        "y": 43
                      },
                      {
                        "x": 2762,
                        "y": 38
                      },
                      {
                        "x": 2763,
                        "y": 199
                      },
                      {
                        "x": 1047,
                        "y": 204
                      }
                    ],
                    "valueProb": 100
                  },
                  {
                    "key": "formType",
                    "keyProb": 100,
                    "value": "",
                    "valueProb": 100
                  },
                  {
                    "key": "invoiceType",
                    "keyProb": 100,
                    "value": "数电专用发票",
                    "valuePos": [
                      {
                        "x": 1047,
                        "y": 43
                      },
                      {
                        "x": 2762,
                        "y": 38
                      },
                      {
                        "x": 2763,
                        "y": 199
                      },
                      {
                        "x": 1047,
                        "y": 204
                      }
                    ],
                    "valueProb": 100
                  },
                  {
                    "key": "specialTag",
                    "keyProb": 100,
                    "value": "",
                    "valueProb": 100
                  },
                  {
                    "key": "invoiceDetails",
                    "keyProb": 100,
                    "value": "[{\"itemName\":\"*住宿服务*住宿费\",\"specification\":\"高级双床房\",\"unit\":\"天\",\"quantity\":\"1\",\"unitPrice\":\"254.7227722772277\",\"amount\":\"254.72\",\"taxRate\":\"1%\",\"tax\":\"2.55\"}]",
                    "valueProb": 100
                  }
                ],
                "sliceRect": {
                  "x0": 66,
                  "y0": 104,
                  "x1": 4042,
                  "y1": 102,
                  "x2": 4045,
                  "y2": 2609,
                  "x3": 66,
                  "y3": 2610
                },
                "width": 3980
              },
              "sliceRect": {
                "x0": 66,
                "y0": 104,
                "x1": 4042,
                "y1": 102,
                "x2": 4045,
                "y2": 2609,
                "x3": 66,
                "y3": 2610
              },
              "type": "增值税发票"
            }
          ],
          "width": 4092
        },
        "usedAction": "RecognizeMixedInvoices",
        "providerRequestId": "715E8FF4-99DC-5A87-9B2A-EF3FCD0D0F51",
        "providerCode": "",
        "providerMessage": ""
      },
      "createdAt": "2026-03-04T15:51:42.137Z",
      "importedAt": "2026-03-04T15:51:42.137Z"
    }
  ],
  "entries": [
    {
      "id": "20b338cc-194c-4c45-885f-3c5cd5218991",
      "documentId": "9207975c-8ad0-436e-911e-b0f3edbd9f56",
      "sourceIndex": 0,
      "invoiceType": "数电普通发票",
      "title": "电子发票(普通发票)",
      "occurredDate": "2026-01-09",
      "invoiceDate": "2026-01-06",
      "createdAt": "2026-03-04T13:51:00.000Z",
      "expenseCategory": "餐饮",
      "expenseSubCategory": "UNKNOWN",
      "currency": "CNY",
      "merchantName": "北京浩扬餐饮管理有限公司",
      "sellerName": "北京浩扬餐饮管理有限公司",
      "sellerTaxNumber": "91110105MA009X0B64",
      "purchaserName": "科宏昌(北京)医疗仪器有限公司",
      "purchaserTaxNumber": "91110105675701542D",
      "invoiceCode": "",
      "invoiceNumber": "26112000000068159896",
      "checkCode": "",
      "machineCode": "",
      "routeFrom": "",
      "routeTo": "",
      "travelerName": "",
      "seatClass": "",
      "entryType": "INVOICE_LINE",
      "amount": 756.44,
      "amountExcludingTax": 756.44,
      "taxAmount": 7.56,
      "itemName": "*餐饮服务*餐饮服务",
      "specification": "",
      "unit": "",
      "quantity": null,
      "unitPrice": null,
      "rawFields": {
        "detailIndex": 0,
        "detail": {
          "itemName": "*餐饮服务*餐饮服务",
          "specification": "",
          "unit": "",
          "quantity": "",
          "unitPrice": "",
          "amount": "756.44",
          "taxRate": "1%",
          "tax": "7.56"
        },
        "common": {
          "title": "电子发票(普通发票)",
          "invoiceType": "数电普通发票",
          "invoiceDate": "2026-01-06",
          "amount": 764,
          "amountExcludingTax": 756.44,
          "taxAmount": 7.56,
          "currency": "CNY",
          "invoiceCode": "",
          "invoiceNumber": "26112000000068159896",
          "checkCode": "",
          "machineCode": "",
          "sellerName": "北京浩扬餐饮管理有限公司",
          "sellerTaxNumber": "91110105MA009X0B64",
          "purchaserName": "科宏昌(北京)医疗仪器有限公司",
          "purchaserTaxNumber": "91110105675701542D",
          "routeFrom": "",
          "routeTo": "",
          "travelerName": "",
          "transportNo": "",
          "seatClass": "",
          "expenseCategory": "餐饮",
          "docSubType": "UNKNOWN"
        },
        "root": {
          "invoiceCode": "",
          "invoiceNumber": "26112000000068159896",
          "printedInvoiceCode": "",
          "printedInvoiceNumber": "",
          "invoiceDate": "2026年01月06日",
          "machineCode": "",
          "checkCode": "",
          "purchaserName": "科宏昌(北京)医疗仪器有限公司",
          "purchaserTaxNumber": "91110105675701542D",
          "purchaserContactInfo": "",
          "purchaserBankAccountInfo": "",
          "passwordArea": "",
          "invoiceAmountPreTax": "756.44",
          "invoiceTax": "7.56",
          "totalAmountInWords": "柒佰陆拾肆圆整",
          "totalAmount": "764.00",
          "sellerName": "北京浩扬餐饮管理有限公司",
          "sellerTaxNumber": "91110105MA009X0B64",
          "sellerContactInfo": "",
          "sellerBankAccountInfo": "",
          "recipient": "",
          "reviewer": "",
          "drawer": "刘国辉",
          "remarks": "",
          "title": "电子发票(普通发票)",
          "formType": "",
          "invoiceType": "数电普通发票",
          "specialTag": "",
          "invoiceDetails": [
            {
              "itemName": "*餐饮服务*餐饮服务",
              "specification": "",
              "unit": "",
              "quantity": "",
              "unitPrice": "",
              "amount": "756.44",
              "taxRate": "1%",
              "tax": "7.56"
            }
          ]
        }
      },
      "selfPaid": true,
      "occurredRegion": "郑州"
    },
    {
      "id": "304a4ed4-264f-4392-b550-3d7d99fd5d06",
      "documentId": "716f5ed1-e8ba-4b0b-922e-e0ef1806a57a",
      "sourceIndex": 0,
      "invoiceType": "数电普通发票",
      "title": "电子发票(普通发票)",
      "occurredDate": "2026-01-03",
      "invoiceDate": "2026-01-03",
      "createdAt": "2026-03-04T13:51:51.956Z",
      "expenseCategory": "餐饮",
      "expenseSubCategory": "UNKNOWN",
      "currency": "CNY",
      "merchantName": "北京小大董三里屯餐饮有限公司",
      "sellerName": "北京小大董三里屯餐饮有限公司",
      "sellerTaxNumber": "91110105MA01UHAT9W",
      "purchaserName": "科宏昌(北京)医疗仪器有限公司",
      "purchaserTaxNumber": "91110105675701542D",
      "invoiceCode": "",
      "invoiceNumber": "26112000000016867066",
      "checkCode": "",
      "machineCode": "",
      "routeFrom": "",
      "routeTo": "",
      "travelerName": "",
      "seatClass": "",
      "entryType": "INVOICE_LINE",
      "amount": 240.57,
      "amountExcludingTax": 240.57,
      "taxAmount": 14.43,
      "itemName": "*餐饮服务*餐饮服务",
      "specification": "",
      "unit": "",
      "quantity": 1,
      "unitPrice": 240.57,
      "rawFields": {
        "detailIndex": 0,
        "detail": {
          "itemName": "*餐饮服务*餐饮服务",
          "specification": "",
          "unit": "",
          "quantity": "1",
          "unitPrice": "240.57",
          "amount": "240.57",
          "taxRate": "6%",
          "tax": "14.43"
        },
        "common": {
          "title": "电子发票(普通发票)",
          "invoiceType": "数电普通发票",
          "invoiceDate": "2026-01-03",
          "amount": 255,
          "amountExcludingTax": 240.57,
          "taxAmount": 14.43,
          "currency": "CNY",
          "invoiceCode": "",
          "invoiceNumber": "26112000000016867066",
          "checkCode": "",
          "machineCode": "",
          "sellerName": "北京小大董三里屯餐饮有限公司",
          "sellerTaxNumber": "91110105MA01UHAT9W",
          "purchaserName": "科宏昌(北京)医疗仪器有限公司",
          "purchaserTaxNumber": "91110105675701542D",
          "routeFrom": "",
          "routeTo": "",
          "travelerName": "",
          "transportNo": "",
          "seatClass": "",
          "expenseCategory": "餐饮",
          "docSubType": "UNKNOWN"
        },
        "root": {
          "invoiceCode": "",
          "invoiceNumber": "26112000000016867066",
          "printedInvoiceCode": "",
          "printedInvoiceNumber": "",
          "invoiceDate": "2026年01月03日",
          "machineCode": "",
          "checkCode": "",
          "purchaserName": "科宏昌(北京)医疗仪器有限公司",
          "purchaserTaxNumber": "91110105675701542D",
          "purchaserContactInfo": "",
          "purchaserBankAccountInfo": "",
          "passwordArea": "",
          "invoiceAmountPreTax": "240.57",
          "invoiceTax": "14.43",
          "totalAmountInWords": "贰佰伍拾伍圆整",
          "totalAmount": "255.00",
          "sellerName": "北京小大董三里屯餐饮有限公司",
          "sellerTaxNumber": "91110105MA01UHAT9W",
          "sellerContactInfo": "",
          "sellerBankAccountInfo": "",
          "recipient": "",
          "reviewer": "",
          "drawer": "赵磊",
          "remarks": "",
          "title": "电子发票(普通发票)",
          "formType": "",
          "invoiceType": "数电普通发票",
          "specialTag": "",
          "invoiceDetails": [
            {
              "itemName": "*餐饮服务*餐饮服务",
              "specification": "",
              "unit": "",
              "quantity": "1",
              "unitPrice": "240.57",
              "amount": "240.57",
              "taxRate": "6%",
              "tax": "14.43"
            }
          ]
        }
      },
      "selfPaid": true,
      "occurredRegion": "郑州"
    },
    {
      "id": "aaa837b6-0ef7-4ff0-a6dc-deffee8b5ea7",
      "documentId": "70dcaf8e-bf99-4afb-a9a9-8c737fa64926",
      "sourceIndex": 0,
      "invoiceType": "数电专用发票",
      "title": "电子发票(增值税专用发票)",
      "occurredDate": "2026-02-07",
      "invoiceDate": "2026-02-07",
      "createdAt": "2026-03-04T15:51:00.000Z",
      "expenseCategory": "住宿",
      "expenseSubCategory": "VAT_INVOICE",
      "currency": "CNY",
      "merchantName": "许昌兴华酒店管理有限公司",
      "sellerName": "许昌兴华酒店管理有限公司",
      "sellerTaxNumber": "91411002MA9MA11C53",
      "purchaserName": "科宏昌(北京)医疗仪器有限公司",
      "purchaserTaxNumber": "91110105675701542D",
      "invoiceCode": "",
      "invoiceNumber": "26412000000470619046",
      "checkCode": "",
      "machineCode": "",
      "routeFrom": "",
      "routeTo": "",
      "travelerName": "",
      "selfPaid": true,
      "occurredRegion": "郑州",
      "seatClass": "",
      "entryType": "INVOICE_LINE",
      "amount": 254.72,
      "amountExcludingTax": 254.72,
      "taxAmount": 2.55,
      "itemName": "*住宿服务*住宿费",
      "specification": "高级双床房",
      "unit": "天",
      "quantity": 1,
      "unitPrice": 254.72,
      "rawFields": {
        "detailIndex": 0,
        "detail": {
          "itemName": "*住宿服务*住宿费",
          "specification": "高级双床房",
          "unit": "天",
          "quantity": "1",
          "unitPrice": "254.7227722772277",
          "amount": "254.72",
          "taxRate": "1%",
          "tax": "2.55"
        },
        "common": {
          "title": "电子发票(增值税专用发票)",
          "invoiceType": "数电专用发票",
          "invoiceDate": "2026-02-07",
          "amount": 257.27,
          "amountExcludingTax": 254.72,
          "taxAmount": 2.55,
          "currency": "CNY",
          "invoiceCode": "",
          "invoiceNumber": "26412000000470619046",
          "checkCode": "",
          "machineCode": "",
          "sellerName": "许昌兴华酒店管理有限公司",
          "sellerTaxNumber": "91411002MA9MA11C53",
          "purchaserName": "科宏昌(北京)医疗仪器有限公司",
          "purchaserTaxNumber": "91110105675701542D",
          "routeFrom": "",
          "routeTo": "",
          "travelerName": "",
          "seatClass": "",
          "expenseCategory": "住宿",
          "docSubType": "VAT_INVOICE",
          "occurredRegion": ""
        },
        "root": {
          "invoiceCode": "",
          "invoiceNumber": "26412000000470619046",
          "printedInvoiceCode": "",
          "printedInvoiceNumber": "",
          "invoiceDate": "2026年02月07日",
          "machineCode": "",
          "checkCode": "",
          "purchaserName": "科宏昌(北京)医疗仪器有限公司",
          "purchaserTaxNumber": "91110105675701542D",
          "purchaserContactInfo": "",
          "purchaserBankAccountInfo": "",
          "passwordArea": "",
          "invoiceAmountPreTax": "254.72",
          "invoiceTax": "2.55",
          "totalAmountInWords": "贰佰伍拾柒圆贰角柒分",
          "totalAmount": "257.27",
          "sellerName": "许昌兴华酒店管理有限公司",
          "sellerTaxNumber": "91411002MA9MA11C53",
          "sellerContactInfo": "",
          "sellerBankAccountInfo": "",
          "recipient": "",
          "reviewer": "",
          "drawer": "王晋格",
          "remarks": "购买方地址:北京市朝阳区慈云寺北里118号楼8层801等[17]套内17层1701内03A、04、05室;电话:010-85752300;购方开户银行:招行北京东四环支行;银行账号:110906139710401;销售方地址:河南省许昌市魏都区颍昌大道绿洲梦想广场电话:0374-3137777;销方开户银行:中原银行股份有限公司许昌颖昌路支行;银行账号:411010010140035101;汉庭许昌胖东来生活广场酒店,入离日期:1-31至2-1,共1天,共1间",
          "title": "电子发票(增值税专用发票)",
          "formType": "",
          "invoiceType": "数电专用发票",
          "specialTag": "",
          "invoiceDetails": [
            {
              "itemName": "*住宿服务*住宿费",
              "specification": "高级双床房",
              "unit": "天",
              "quantity": "1",
              "unitPrice": "254.7227722772277",
              "amount": "254.72",
              "taxRate": "1%",
              "tax": "2.55"
            }
          ]
        }
      }
    },
    {
      "id": "0fe63234-3051-416c-9b55-03bb771565fb",
      "documentId": "",
      "sourceIndex": 0,
      "entryType": "INVOICE_MANUAL",
      "expenseCategory": "火车票",
      "expenseSubCategory": "手工录入",
      "invoiceType": "手工票据",
      "title": "郑州-禹州",
      "occurredDate": "2026-02-04",
      "invoiceDate": "2026-02-04",
      "createdAt": "2026-03-04T15:52:24.376Z",
      "amount": 123,
      "amountExcludingTax": null,
      "taxAmount": null,
      "currency": "CNY",
      "merchantName": "",
      "sellerName": "",
      "sellerTaxNumber": "",
      "purchaserName": "",
      "purchaserTaxNumber": "",
      "invoiceCode": "",
      "invoiceNumber": "",
      "selfPaid": false,
      "occurredRegion": "北京",
      "checkCode": "",
      "machineCode": "",
      "routeFrom": "",
      "routeTo": "",
      "travelerName": "",
      "seatClass": "",
      "itemName": "郑州-禹州",
      "specification": "",
      "unit": "",
      "quantity": null,
      "unitPrice": null,
      "rawFields": {
        "manual": true,
        "createdBy": "MANUAL_DIALOG"
      }
    }
  ],
  "ocrJobs": [
    {
      "id": "0d3927d3-b224-447b-ade7-cae78794c02d",
      "documentId": "35eaf133-23a2-4daf-abee-027a2aba621d",
      "traceId": "ae6fd257-6e8e-4b16-a0f8-4d8895e3c669",
      "source": "ALIYUN_OCR",
      "status": "SUCCESS",
      "startedAt": "2026-03-04T08:29:29.705Z",
      "endedAt": "2026-03-04T08:29:31.116Z",
      "elapsedMs": 1409,
      "actions": [
        {
          "name": "RecognizeMixedInvoices",
          "statusCode": 200,
          "providerCode": "",
          "requestId": "D478646D-E30A-5B9C-B7A5-687AF222367B",
          "message": "",
          "hasData": true,
          "elapsedMs": 1393,
          "attempt": 1
        }
      ],
      "errorMessage": "",
      "errorStack": "",
      "createdAt": "2026-03-04T08:29:29.705Z"
    },
    {
      "id": "da6775e2-16f6-4bba-85dd-42631e81dc39",
      "documentId": "4cb4fa93-6566-433f-9be2-2ff964f36d52",
      "traceId": "ce80f170-0356-4d37-b943-11b1ca202cb0",
      "source": "DOCX_TEXT",
      "status": "SUCCESS",
      "startedAt": "2026-03-04T08:29:31.147Z",
      "endedAt": "2026-03-04T08:29:31.254Z",
      "elapsedMs": 105,
      "actions": [
        {
          "name": "ParseDocx",
          "statusCode": 200,
          "providerCode": "OK",
          "requestId": "",
          "message": "",
          "hasData": false,
          "elapsedMs": 105
        }
      ],
      "errorMessage": "",
      "errorStack": "",
      "createdAt": "2026-03-04T08:29:31.147Z"
    },
    {
      "id": "bbb3a844-3fd3-472f-8bbb-48ca8f7ab9b0",
      "documentId": "29385e1d-6d9f-4ef9-b82e-761ec7a992da",
      "traceId": "f8a4488a-17db-4ce0-a11d-000b4fa1aa3c",
      "source": "DOCX_TEXT",
      "status": "SUCCESS",
      "startedAt": "2026-03-04T08:30:03.856Z",
      "endedAt": "2026-03-04T08:30:03.926Z",
      "elapsedMs": 68,
      "actions": [
        {
          "name": "ParseDocx",
          "statusCode": 200,
          "providerCode": "OK",
          "requestId": "",
          "message": "",
          "hasData": false,
          "elapsedMs": 68
        }
      ],
      "errorMessage": "",
      "errorStack": "",
      "createdAt": "2026-03-04T08:30:03.856Z"
    },
    {
      "id": "2cbdbdcf-d00e-4d59-bb74-afefe9de0154",
      "documentId": "75c740f6-ef65-462b-ad07-2568c318c9c5",
      "traceId": "87befd49-cf67-4fc8-b135-05fc426c7913",
      "source": "DOCX_TEXT",
      "status": "SUCCESS",
      "startedAt": "2026-03-04T08:30:20.852Z",
      "endedAt": "2026-03-04T08:30:20.966Z",
      "elapsedMs": 112,
      "actions": [
        {
          "name": "ParseDocx",
          "statusCode": 200,
          "providerCode": "OK",
          "requestId": "",
          "message": "",
          "hasData": false,
          "elapsedMs": 112
        }
      ],
      "errorMessage": "",
      "errorStack": "",
      "createdAt": "2026-03-04T08:30:20.852Z"
    },
    {
      "id": "bcf5ea50-42ec-41c8-82a4-5168e9a7e056",
      "documentId": "7dcf59ec-cdff-46c9-9f62-1525e3d6280c",
      "traceId": "74bf2e62-f4ad-4ae7-8df9-88bd24356faa",
      "source": "DOCX_TEXT",
      "status": "SUCCESS",
      "startedAt": "2026-03-04T08:30:57.395Z",
      "endedAt": "2026-03-04T08:30:57.447Z",
      "elapsedMs": 49,
      "actions": [
        {
          "name": "ParseDocx",
          "statusCode": 200,
          "providerCode": "OK",
          "requestId": "",
          "message": "",
          "hasData": false,
          "elapsedMs": 49
        }
      ],
      "errorMessage": "",
      "errorStack": "",
      "createdAt": "2026-03-04T08:30:57.395Z"
    },
    {
      "id": "08fb1d90-d1f0-4475-9b12-e9c681b422c4",
      "documentId": "1364ec64-b1c3-4994-8bdf-4f37d1cdd6da",
      "traceId": "74f1f48a-2114-4d7a-924b-d981aebd4635",
      "source": "DOCX_TEXT",
      "status": "SUCCESS",
      "startedAt": "2026-03-04T08:31:07.137Z",
      "endedAt": "2026-03-04T08:31:07.233Z",
      "elapsedMs": 94,
      "actions": [
        {
          "name": "ParseDocx",
          "statusCode": 200,
          "providerCode": "OK",
          "requestId": "",
          "message": "",
          "hasData": false,
          "elapsedMs": 94
        }
      ],
      "errorMessage": "",
      "errorStack": "",
      "createdAt": "2026-03-04T08:31:07.137Z"
    },
    {
      "id": "2c11d414-04c5-46ef-8e52-14ddd18ccf49",
      "documentId": "9207975c-8ad0-436e-911e-b0f3edbd9f56",
      "traceId": "ea909117-ec88-4e0f-b4f9-5824aeb651a5",
      "source": "ALIYUN_OCR",
      "status": "SUCCESS",
      "startedAt": "2026-03-04T13:51:35.019Z",
      "endedAt": "2026-03-04T13:51:38.382Z",
      "elapsedMs": 3363,
      "actions": [
        {
          "name": "RecognizeMixedInvoices",
          "statusCode": 200,
          "providerCode": "",
          "requestId": "1F7FD861-73CD-52F8-B3CF-8B3A74E10FE7",
          "message": "",
          "hasData": true,
          "elapsedMs": 3357,
          "attempt": 1
        }
      ],
      "errorMessage": "",
      "errorStack": "",
      "createdAt": "2026-03-04T13:51:35.019Z"
    },
    {
      "id": "5cdb1949-97fc-4366-84e5-bd20256d6145",
      "documentId": "716f5ed1-e8ba-4b0b-922e-e0ef1806a57a",
      "traceId": "2a416958-1b43-4e72-8d98-bce57bd055c7",
      "source": "ALIYUN_OCR",
      "status": "SUCCESS",
      "startedAt": "2026-03-04T13:51:51.956Z",
      "endedAt": "2026-03-04T13:51:53.695Z",
      "elapsedMs": 1739,
      "actions": [
        {
          "name": "RecognizeMixedInvoices",
          "statusCode": 200,
          "providerCode": "",
          "requestId": "0B432DE8-FCB3-5970-93D3-06AF4B968577",
          "message": "",
          "hasData": true,
          "elapsedMs": 1736,
          "attempt": 1
        }
      ],
      "errorMessage": "",
      "errorStack": "",
      "createdAt": "2026-03-04T13:51:51.956Z"
    },
    {
      "id": "1eecb253-45de-4f7f-9164-f39e6cc11138",
      "documentId": "70dcaf8e-bf99-4afb-a9a9-8c737fa64926",
      "traceId": "8a99f0ba-495d-4332-9b97-23fcfd6385d0",
      "source": "ALIYUN_OCR",
      "status": "SUCCESS",
      "startedAt": "2026-03-04T15:51:42.137Z",
      "endedAt": "2026-03-04T15:51:44.892Z",
      "elapsedMs": 2755,
      "actions": [
        {
          "name": "RecognizeMixedInvoices",
          "statusCode": 200,
          "providerCode": "",
          "requestId": "715E8FF4-99DC-5A87-9B2A-EF3FCD0D0F51",
          "message": "",
          "hasData": true,
          "elapsedMs": 2749,
          "attempt": 1
        }
      ],
      "errorMessage": "",
      "errorStack": "",
      "createdAt": "2026-03-04T15:51:42.137Z"
    }
  ]
}